[
  {
    "user_id":"7778267b-cdff-45c5-9616-4f3b07af9758",
    "match_id":"711c9a67-dd8c-4070-90e4-c606b89c007d.nakama-0",
    "map_id":"GrandRift",
    "x":-225.8942871094,
    "y":32.3040046692,
    "z":39.4559783936,
    "ts":1770715988,
    "event":"Position"
  },
  {
    "user_id":"7778267b-cdff-45c5-9616-4f3b07af9758",
    "match_id":"711c9a67-dd8c-4070-90e4-c606b89c007d.nakama-0",
    "map_id":"GrandRift",
    "x":-214.4456481934,
    "y":34.1241950989,
    "z":33.6239471436,
    "ts":1770716008,
    "event":"Position"
  },
  {
    "user_id":"7778267b-cdff-45c5-9616-4f3b07af9758",
    "match_id":"711c9a67-dd8c-4070-90e4-c606b89c007d.nakama-0",
    "map_id":"GrandRift",
    "x":-190.6571350098,
    "y":39.8620223999,
    "z":36.0990066528,
    "ts":1770716013,
    "event":"Position"
  },
  {
    "user_id":"7778267b-cdff-45c5-9616-4f3b07af9758",
    "match_id":"711c9a67-dd8c-4070-90e4-c606b89c007d.nakama-0",
    "map_id":"GrandRift",
    "x":-178.3709564209,
    "y":40.1137123108,
    "z":33.055305481,
    "ts":1770716018,
    "event":"Position"
  },
  {
    "user_id":"7778267b-cdff-45c5-9616-4f3b07af9758",
    "match_id":"711c9a67-dd8c-4070-90e4-c606b89c007d.nakama-0",
    "map_id":"GrandRift",
    "x":-172.7909851074,
    "y":40.109287262,
    "z":32.3837966919,
    "ts":1770716023,
    "event":"Position"
  },
  {
    "user_id":"7778267b-cdff-45c5-9616-4f3b07af9758",
    "match_id":"711c9a67-dd8c-4070-90e4-c606b89c007d.nakama-0",
    "map_id":"GrandRift",
    "x":-169.9618682861,
    "y":40.4458312988,
    "z":27.86469841,
    "ts":1770716028,
    "event":"Position"
  },
  {
    "user_id":"7778267b-cdff-45c5-9616-4f3b07af9758",
    "match_id":"711c9a67-dd8c-4070-90e4-c606b89c007d.nakama-0",
    "map_id":"GrandRift",
    "x":-163.7645111084,
    "y":40.4024162292,
    "z":22.4331436157,
    "ts":1770716033,
    "event":"Position"
  },
  {
    "user_id":"7778267b-cdff-45c5-9616-4f3b07af9758",
    "match_id":"711c9a67-dd8c-4070-90e4-c606b89c007d.nakama-0",
    "map_id":"GrandRift",
    "x":-158.830581665,
    "y":40.451789856,
    "z":18.7413768768,
    "ts":1770716038,
    "event":"Position"
  },
  {
    "user_id":"7778267b-cdff-45c5-9616-4f3b07af9758",
    "match_id":"711c9a67-dd8c-4070-90e4-c606b89c007d.nakama-0",
    "map_id":"GrandRift",
    "x":-153.5414733887,
    "y":39.5748176575,
    "z":13.4286699295,
    "ts":1770716043,
    "event":"Position"
  },
  {
    "user_id":"7778267b-cdff-45c5-9616-4f3b07af9758",
    "match_id":"711c9a67-dd8c-4070-90e4-c606b89c007d.nakama-0",
    "map_id":"GrandRift",
    "x":-140.8711395264,
    "y":38.8763542175,
    "z":15.25004673,
    "ts":1770716048,
    "event":"Position"
  },
  {
    "user_id":"7778267b-cdff-45c5-9616-4f3b07af9758",
    "match_id":"711c9a67-dd8c-4070-90e4-c606b89c007d.nakama-0",
    "map_id":"GrandRift",
    "x":-134.5732574463,
    "y":39.0295143127,
    "z":26.3417816162,
    "ts":1770716053,
    "event":"Position"
  },
  {
    "user_id":"7778267b-cdff-45c5-9616-4f3b07af9758",
    "match_id":"711c9a67-dd8c-4070-90e4-c606b89c007d.nakama-0",
    "map_id":"GrandRift",
    "x":-145.5413970947,
    "y":38.9260406494,
    "z":42.0230522156,
    "ts":1770716058,
    "event":"Position"
  },
  {
    "user_id":"7778267b-cdff-45c5-9616-4f3b07af9758",
    "match_id":"711c9a67-dd8c-4070-90e4-c606b89c007d.nakama-0",
    "map_id":"GrandRift",
    "x":-149.0229949951,
    "y":33.2667770386,
    "z":54.873134613,
    "ts":1770716063,
    "event":"Position"
  },
  {
    "user_id":"7778267b-cdff-45c5-9616-4f3b07af9758",
    "match_id":"711c9a67-dd8c-4070-90e4-c606b89c007d.nakama-0",
    "map_id":"GrandRift",
    "x":-140.1483154297,
    "y":32.9312553406,
    "z":81.0681762695,
    "ts":1770716068,
    "event":"Position"
  },
  {
    "user_id":"7778267b-cdff-45c5-9616-4f3b07af9758",
    "match_id":"711c9a67-dd8c-4070-90e4-c606b89c007d.nakama-0",
    "map_id":"GrandRift",
    "x":-133.893447876,
    "y":26.3451576233,
    "z":98.7462234497,
    "ts":1770716073,
    "event":"Position"
  },
  {
    "user_id":"7778267b-cdff-45c5-9616-4f3b07af9758",
    "match_id":"711c9a67-dd8c-4070-90e4-c606b89c007d.nakama-0",
    "map_id":"GrandRift",
    "x":-151.0261230469,
    "y":17.9748210907,
    "z":113.2853012085,
    "ts":1770716078,
    "event":"Position"
  },
  {
    "user_id":"7778267b-cdff-45c5-9616-4f3b07af9758",
    "match_id":"711c9a67-dd8c-4070-90e4-c606b89c007d.nakama-0",
    "map_id":"GrandRift",
    "x":-130.4122772217,
    "y":17.8608798981,
    "z":135.0753479004,
    "ts":1770716083,
    "event":"Position"
  },
  {
    "user_id":"7778267b-cdff-45c5-9616-4f3b07af9758",
    "match_id":"711c9a67-dd8c-4070-90e4-c606b89c007d.nakama-0",
    "map_id":"GrandRift",
    "x":-120.1961135864,
    "y":17.8058261871,
    "z":137.1076049805,
    "ts":1770716088,
    "event":"Position"
  },
  {
    "user_id":"7778267b-cdff-45c5-9616-4f3b07af9758",
    "match_id":"711c9a67-dd8c-4070-90e4-c606b89c007d.nakama-0",
    "map_id":"GrandRift",
    "x":-119.1006240845,
    "y":17.9420986176,
    "z":133.7185974121,
    "ts":1770716093,
    "event":"Position"
  },
  {
    "user_id":"7778267b-cdff-45c5-9616-4f3b07af9758",
    "match_id":"711c9a67-dd8c-4070-90e4-c606b89c007d.nakama-0",
    "map_id":"GrandRift",
    "x":-115.2145080566,
    "y":20.384021759,
    "z":132.0831451416,
    "ts":1770716098,
    "event":"Position"
  },
  {
    "user_id":"7778267b-cdff-45c5-9616-4f3b07af9758",
    "match_id":"711c9a67-dd8c-4070-90e4-c606b89c007d.nakama-0",
    "map_id":"GrandRift",
    "x":-99.2549819946,
    "y":20.3936805725,
    "z":137.8221740723,
    "ts":1770716103,
    "event":"Position"
  },
  {
    "user_id":"7778267b-cdff-45c5-9616-4f3b07af9758",
    "match_id":"711c9a67-dd8c-4070-90e4-c606b89c007d.nakama-0",
    "map_id":"GrandRift",
    "x":-92.7864837646,
    "y":20.3936805725,
    "z":141.347366333,
    "ts":1770716108,
    "event":"Position"
  },
  {
    "user_id":"7778267b-cdff-45c5-9616-4f3b07af9758",
    "match_id":"711c9a67-dd8c-4070-90e4-c606b89c007d.nakama-0",
    "map_id":"GrandRift",
    "x":-68.1205062866,
    "y":20.8630008698,
    "z":125.5039749146,
    "ts":1770716113,
    "event":"Position"
  },
  {
    "user_id":"7778267b-cdff-45c5-9616-4f3b07af9758",
    "match_id":"711c9a67-dd8c-4070-90e4-c606b89c007d.nakama-0",
    "map_id":"GrandRift",
    "x":-38.0044441223,
    "y":21.8742618561,
    "z":113.2060928345,
    "ts":1770716119,
    "event":"Position"
  },
  {
    "user_id":"7778267b-cdff-45c5-9616-4f3b07af9758",
    "match_id":"711c9a67-dd8c-4070-90e4-c606b89c007d.nakama-0",
    "map_id":"GrandRift",
    "x":-13.7313184738,
    "y":20.4281692505,
    "z":103.4217071533,
    "ts":1770716124,
    "event":"Position"
  },
  {
    "user_id":"7778267b-cdff-45c5-9616-4f3b07af9758",
    "match_id":"711c9a67-dd8c-4070-90e4-c606b89c007d.nakama-0",
    "map_id":"GrandRift",
    "x":17.7162723541,
    "y":24.5478878021,
    "z":105.4240112305,
    "ts":1770716129,
    "event":"Position"
  },
  {
    "user_id":"7778267b-cdff-45c5-9616-4f3b07af9758",
    "match_id":"711c9a67-dd8c-4070-90e4-c606b89c007d.nakama-0",
    "map_id":"GrandRift",
    "x":38.0885505676,
    "y":28.6461906433,
    "z":109.4862518311,
    "ts":1770716134,
    "event":"Position"
  },
  {
    "user_id":"7778267b-cdff-45c5-9616-4f3b07af9758",
    "match_id":"711c9a67-dd8c-4070-90e4-c606b89c007d.nakama-0",
    "map_id":"GrandRift",
    "x":55.5070800781,
    "y":33.7652015686,
    "z":108.2447509766,
    "ts":1770716139,
    "event":"Position"
  },
  {
    "user_id":"7778267b-cdff-45c5-9616-4f3b07af9758",
    "match_id":"711c9a67-dd8c-4070-90e4-c606b89c007d.nakama-0",
    "map_id":"GrandRift",
    "x":69.8893814087,
    "y":36.1856002808,
    "z":97.4749755859,
    "ts":1770716144,
    "event":"Position"
  },
  {
    "user_id":"7778267b-cdff-45c5-9616-4f3b07af9758",
    "match_id":"711c9a67-dd8c-4070-90e4-c606b89c007d.nakama-0",
    "map_id":"GrandRift",
    "x":89.39402771,
    "y":36.1714439392,
    "z":89.4770965576,
    "ts":1770716149,
    "event":"Position"
  },
  {
    "user_id":"7778267b-cdff-45c5-9616-4f3b07af9758",
    "match_id":"711c9a67-dd8c-4070-90e4-c606b89c007d.nakama-0",
    "map_id":"GrandRift",
    "x":109.8638381958,
    "y":35.610496521,
    "z":78.8436584473,
    "ts":1770716154,
    "event":"Position"
  },
  {
    "user_id":"7778267b-cdff-45c5-9616-4f3b07af9758",
    "match_id":"711c9a67-dd8c-4070-90e4-c606b89c007d.nakama-0",
    "map_id":"GrandRift",
    "x":133.0124816895,
    "y":35.3626289368,
    "z":60.9158439636,
    "ts":1770716159,
    "event":"Position"
  },
  {
    "user_id":"7778267b-cdff-45c5-9616-4f3b07af9758",
    "match_id":"711c9a67-dd8c-4070-90e4-c606b89c007d.nakama-0",
    "map_id":"GrandRift",
    "x":152.5462493896,
    "y":28.8502407074,
    "z":45.499382019,
    "ts":1770716164,
    "event":"Position"
  },
  {
    "user_id":"7778267b-cdff-45c5-9616-4f3b07af9758",
    "match_id":"711c9a67-dd8c-4070-90e4-c606b89c007d.nakama-0",
    "map_id":"GrandRift",
    "x":175.2387542725,
    "y":25.3935203552,
    "z":23.0232028961,
    "ts":1770716169,
    "event":"Position"
  },
  {
    "user_id":"7778267b-cdff-45c5-9616-4f3b07af9758",
    "match_id":"711c9a67-dd8c-4070-90e4-c606b89c007d.nakama-0",
    "map_id":"GrandRift",
    "x":192.8694152832,
    "y":21.2988529205,
    "z":3.5265803337,
    "ts":1770716174,
    "event":"Position"
  },
  {
    "user_id":"7778267b-cdff-45c5-9616-4f3b07af9758",
    "match_id":"711c9a67-dd8c-4070-90e4-c606b89c007d.nakama-0",
    "map_id":"GrandRift",
    "x":205.2770690918,
    "y":20.6225719452,
    "z":-9.4208211899,
    "ts":1770716179,
    "event":"Position"
  },
  {
    "user_id":"7778267b-cdff-45c5-9616-4f3b07af9758",
    "match_id":"711c9a67-dd8c-4070-90e4-c606b89c007d.nakama-0",
    "map_id":"GrandRift",
    "x":205.207321167,
    "y":21.2117958069,
    "z":-1.7384909391,
    "ts":1770716199,
    "event":"Position"
  },
  {
    "user_id":"7778267b-cdff-45c5-9616-4f3b07af9758",
    "match_id":"711c9a67-dd8c-4070-90e4-c606b89c007d.nakama-0",
    "map_id":"GrandRift",
    "x":207.258392334,
    "y":21.2117958069,
    "z":2.4779169559,
    "ts":1770716204,
    "event":"Position"
  },
  {
    "user_id":"7778267b-cdff-45c5-9616-4f3b07af9758",
    "match_id":"711c9a67-dd8c-4070-90e4-c606b89c007d.nakama-0",
    "map_id":"GrandRift",
    "x":214.5180358887,
    "y":21.1244125366,
    "z":-1.3642081022,
    "ts":1770716209,
    "event":"Position"
  },
  {
    "user_id":"7778267b-cdff-45c5-9616-4f3b07af9758",
    "match_id":"711c9a67-dd8c-4070-90e4-c606b89c007d.nakama-0",
    "map_id":"GrandRift",
    "x":215.5767669678,
    "y":21.0003147125,
    "z":-3.1351337433,
    "ts":1770716214,
    "event":"Position"
  },
  {
    "user_id":"7778267b-cdff-45c5-9616-4f3b07af9758",
    "match_id":"711c9a67-dd8c-4070-90e4-c606b89c007d.nakama-0",
    "map_id":"GrandRift",
    "x":214.4594726562,
    "y":21.11145401,
    "z":-2.0509047508,
    "ts":1770716219,
    "event":"Position"
  },
  {
    "user_id":"7778267b-cdff-45c5-9616-4f3b07af9758",
    "match_id":"711c9a67-dd8c-4070-90e4-c606b89c007d.nakama-0",
    "map_id":"GrandRift",
    "x":210.5885620117,
    "y":21.2329101562,
    "z":-2.8371429443,
    "ts":1770716221,
    "event":"BotKill"
  },
  {
    "user_id":"7778267b-cdff-45c5-9616-4f3b07af9758",
    "match_id":"711c9a67-dd8c-4070-90e4-c606b89c007d.nakama-0",
    "map_id":"GrandRift",
    "x":204.907913208,
    "y":21.2020015717,
    "z":-2.7933769226,
    "ts":1770716224,
    "event":"Position"
  },
  {
    "user_id":"7778267b-cdff-45c5-9616-4f3b07af9758",
    "match_id":"711c9a67-dd8c-4070-90e4-c606b89c007d.nakama-0",
    "map_id":"GrandRift",
    "x":195.694229126,
    "y":20.6299057007,
    "z":-4.4819231033,
    "ts":1770716229,
    "event":"Position"
  },
  {
    "user_id":"7778267b-cdff-45c5-9616-4f3b07af9758",
    "match_id":"711c9a67-dd8c-4070-90e4-c606b89c007d.nakama-0",
    "map_id":"GrandRift",
    "x":195.2220306396,
    "y":20.6761550903,
    "z":-3.9279065132,
    "ts":1770716229,
    "event":"BotKill"
  },
  {
    "user_id":"7778267b-cdff-45c5-9616-4f3b07af9758",
    "match_id":"711c9a67-dd8c-4070-90e4-c606b89c007d.nakama-0",
    "map_id":"GrandRift",
    "x":186.887298584,
    "y":21.1443824768,
    "z":-1.3463028669,
    "ts":1770716234,
    "event":"Position"
  },
  {
    "user_id":"7778267b-cdff-45c5-9616-4f3b07af9758",
    "match_id":"711c9a67-dd8c-4070-90e4-c606b89c007d.nakama-0",
    "map_id":"GrandRift",
    "x":186.887298584,
    "y":21.1443824768,
    "z":-1.3463028669,
    "ts":1770716235,
    "event":"Loot"
  },
  {
    "user_id":"7778267b-cdff-45c5-9616-4f3b07af9758",
    "match_id":"711c9a67-dd8c-4070-90e4-c606b89c007d.nakama-0",
    "map_id":"GrandRift",
    "x":204.3227233887,
    "y":21.22706604,
    "z":0.9244623184,
    "ts":1770716239,
    "event":"Position"
  },
  {
    "user_id":"7778267b-cdff-45c5-9616-4f3b07af9758",
    "match_id":"711c9a67-dd8c-4070-90e4-c606b89c007d.nakama-0",
    "map_id":"GrandRift",
    "x":194.5928497314,
    "y":21.002494812,
    "z":-1.8046450615,
    "ts":1770716254,
    "event":"Position"
  },
  {
    "user_id":"7778267b-cdff-45c5-9616-4f3b07af9758",
    "match_id":"711c9a67-dd8c-4070-90e4-c606b89c007d.nakama-0",
    "map_id":"GrandRift",
    "x":189.0953216553,
    "y":20.9804553986,
    "z":-8.2802696228,
    "ts":1770716258,
    "event":"BotKill"
  },
  {
    "user_id":"7778267b-cdff-45c5-9616-4f3b07af9758",
    "match_id":"711c9a67-dd8c-4070-90e4-c606b89c007d.nakama-0",
    "map_id":"GrandRift",
    "x":189.2447814941,
    "y":20.974407196,
    "z":-8.2522592545,
    "ts":1770716259,
    "event":"Position"
  },
  {
    "user_id":"7778267b-cdff-45c5-9616-4f3b07af9758",
    "match_id":"711c9a67-dd8c-4070-90e4-c606b89c007d.nakama-0",
    "map_id":"GrandRift",
    "x":205.5480499268,
    "y":21.1828765869,
    "z":-3.5622284412,
    "ts":1770716262,
    "event":"BotKill"
  },
  {
    "user_id":"7778267b-cdff-45c5-9616-4f3b07af9758",
    "match_id":"711c9a67-dd8c-4070-90e4-c606b89c007d.nakama-0",
    "map_id":"GrandRift",
    "x":204.1203918457,
    "y":21.2045059204,
    "z":-2.9916114807,
    "ts":1770716264,
    "event":"Position"
  },
  {
    "user_id":"7778267b-cdff-45c5-9616-4f3b07af9758",
    "match_id":"711c9a67-dd8c-4070-90e4-c606b89c007d.nakama-0",
    "map_id":"GrandRift",
    "x":205.7088928223,
    "y":21.2414112091,
    "z":1.8733869791,
    "ts":1770716269,
    "event":"Position"
  },
  {
    "user_id":"7778267b-cdff-45c5-9616-4f3b07af9758",
    "match_id":"711c9a67-dd8c-4070-90e4-c606b89c007d.nakama-0",
    "map_id":"GrandRift",
    "x":205.7088928223,
    "y":21.2414112091,
    "z":1.8733869791,
    "ts":1770716270,
    "event":"Loot"
  },
  {
    "user_id":"7778267b-cdff-45c5-9616-4f3b07af9758",
    "match_id":"711c9a67-dd8c-4070-90e4-c606b89c007d.nakama-0",
    "map_id":"GrandRift",
    "x":205.7088928223,
    "y":21.2414112091,
    "z":1.8733869791,
    "ts":1770716271,
    "event":"Loot"
  },
  {
    "user_id":"7778267b-cdff-45c5-9616-4f3b07af9758",
    "match_id":"711c9a67-dd8c-4070-90e4-c606b89c007d.nakama-0",
    "map_id":"GrandRift",
    "x":205.7088928223,
    "y":21.2414112091,
    "z":1.8733869791,
    "ts":1770716271,
    "event":"Loot"
  },
  {
    "user_id":"7778267b-cdff-45c5-9616-4f3b07af9758",
    "match_id":"711c9a67-dd8c-4070-90e4-c606b89c007d.nakama-0",
    "map_id":"GrandRift",
    "x":205.7088928223,
    "y":21.2414112091,
    "z":1.8733869791,
    "ts":1770716272,
    "event":"Loot"
  },
  {
    "user_id":"7778267b-cdff-45c5-9616-4f3b07af9758",
    "match_id":"711c9a67-dd8c-4070-90e4-c606b89c007d.nakama-0",
    "map_id":"GrandRift",
    "x":202.9143981934,
    "y":21.2414112091,
    "z":2.5292072296,
    "ts":1770716274,
    "event":"Position"
  },
  {
    "user_id":"7778267b-cdff-45c5-9616-4f3b07af9758",
    "match_id":"711c9a67-dd8c-4070-90e4-c606b89c007d.nakama-0",
    "map_id":"GrandRift",
    "x":202.4787597656,
    "y":21.2932929993,
    "z":8.6308984756,
    "ts":1770716279,
    "event":"Position"
  },
  {
    "user_id":"7778267b-cdff-45c5-9616-4f3b07af9758",
    "match_id":"711c9a67-dd8c-4070-90e4-c606b89c007d.nakama-0",
    "map_id":"GrandRift",
    "x":202.2826080322,
    "y":21.2068347931,
    "z":6.6757154465,
    "ts":1770716284,
    "event":"Loot"
  },
  {
    "user_id":"7778267b-cdff-45c5-9616-4f3b07af9758",
    "match_id":"711c9a67-dd8c-4070-90e4-c606b89c007d.nakama-0",
    "map_id":"GrandRift",
    "x":201.9507141113,
    "y":25.9334869385,
    "z":29.2866649628,
    "ts":1770716289,
    "event":"Position"
  },
  {
    "user_id":"7778267b-cdff-45c5-9616-4f3b07af9758",
    "match_id":"711c9a67-dd8c-4070-90e4-c606b89c007d.nakama-0",
    "map_id":"GrandRift",
    "x":201.0337677002,
    "y":30.0605278015,
    "z":45.0651016235,
    "ts":1770716294,
    "event":"Position"
  },
  {
    "user_id":"7778267b-cdff-45c5-9616-4f3b07af9758",
    "match_id":"711c9a67-dd8c-4070-90e4-c606b89c007d.nakama-0",
    "map_id":"GrandRift",
    "x":192.6236114502,
    "y":33.5578727722,
    "z":59.7747383118,
    "ts":1770716300,
    "event":"Position"
  },
  {
    "user_id":"7778267b-cdff-45c5-9616-4f3b07af9758",
    "match_id":"711c9a67-dd8c-4070-90e4-c606b89c007d.nakama-0",
    "map_id":"GrandRift",
    "x":171.3264465332,
    "y":36.3091773987,
    "z":61.5081596375,
    "ts":1770716305,
    "event":"Position"
  },
  {
    "user_id":"7778267b-cdff-45c5-9616-4f3b07af9758",
    "match_id":"711c9a67-dd8c-4070-90e4-c606b89c007d.nakama-0",
    "map_id":"GrandRift",
    "x":153.6150665283,
    "y":36.2977142334,
    "z":52.4219856262,
    "ts":1770716310,
    "event":"Position"
  },
  {
    "user_id":"7778267b-cdff-45c5-9616-4f3b07af9758",
    "match_id":"711c9a67-dd8c-4070-90e4-c606b89c007d.nakama-0",
    "map_id":"GrandRift",
    "x":146.3669128418,
    "y":31.5345649719,
    "z":45.4023551941,
    "ts":1770716320,
    "event":"Position"
  },
  {
    "user_id":"7778267b-cdff-45c5-9616-4f3b07af9758",
    "match_id":"711c9a67-dd8c-4070-90e4-c606b89c007d.nakama-0",
    "map_id":"GrandRift",
    "x":136.0074310303,
    "y":28.422252655,
    "z":29.5899429321,
    "ts":1770716325,
    "event":"Position"
  },
  {
    "user_id":"7778267b-cdff-45c5-9616-4f3b07af9758",
    "match_id":"711c9a67-dd8c-4070-90e4-c606b89c007d.nakama-0",
    "map_id":"GrandRift",
    "x":127.5610122681,
    "y":29.6684494019,
    "z":13.4010248184,
    "ts":1770716330,
    "event":"Position"
  },
  {
    "user_id":"7778267b-cdff-45c5-9616-4f3b07af9758",
    "match_id":"711c9a67-dd8c-4070-90e4-c606b89c007d.nakama-0",
    "map_id":"GrandRift",
    "x":117.154838562,
    "y":31.9260845184,
    "z":-6.0882487297,
    "ts":1770716335,
    "event":"Position"
  },
  {
    "user_id":"7778267b-cdff-45c5-9616-4f3b07af9758",
    "match_id":"711c9a67-dd8c-4070-90e4-c606b89c007d.nakama-0",
    "map_id":"GrandRift",
    "x":108.7525558472,
    "y":28.9368000031,
    "z":-29.2038860321,
    "ts":1770716340,
    "event":"Position"
  },
  {
    "user_id":"7778267b-cdff-45c5-9616-4f3b07af9758",
    "match_id":"711c9a67-dd8c-4070-90e4-c606b89c007d.nakama-0",
    "map_id":"GrandRift",
    "x":97.1337585449,
    "y":27.7931518555,
    "z":-40.5446434021,
    "ts":1770716345,
    "event":"Position"
  },
  {
    "user_id":"7778267b-cdff-45c5-9616-4f3b07af9758",
    "match_id":"711c9a67-dd8c-4070-90e4-c606b89c007d.nakama-0",
    "map_id":"GrandRift",
    "x":79.4750442505,
    "y":24.8358840942,
    "z":-34.0670661926,
    "ts":1770716350,
    "event":"Position"
  },
  {
    "user_id":"7778267b-cdff-45c5-9616-4f3b07af9758",
    "match_id":"711c9a67-dd8c-4070-90e4-c606b89c007d.nakama-0",
    "map_id":"GrandRift",
    "x":61.2018737793,
    "y":27.4849510193,
    "z":-17.5811061859,
    "ts":1770716355,
    "event":"Position"
  },
  {
    "user_id":"7778267b-cdff-45c5-9616-4f3b07af9758",
    "match_id":"711c9a67-dd8c-4070-90e4-c606b89c007d.nakama-0",
    "map_id":"GrandRift",
    "x":33.9960289001,
    "y":26.005859375,
    "z":-0.8955732584,
    "ts":1770716360,
    "event":"Position"
  },
  {
    "user_id":"7778267b-cdff-45c5-9616-4f3b07af9758",
    "match_id":"711c9a67-dd8c-4070-90e4-c606b89c007d.nakama-0",
    "map_id":"GrandRift",
    "x":11.2682971954,
    "y":23.3551826477,
    "z":9.7986040115,
    "ts":1770716365,
    "event":"Position"
  },
  {
    "user_id":"7778267b-cdff-45c5-9616-4f3b07af9758",
    "match_id":"711c9a67-dd8c-4070-90e4-c606b89c007d.nakama-0",
    "map_id":"GrandRift",
    "x":-1.1872918606,
    "y":26.0372047424,
    "z":24.4011859894,
    "ts":1770716370,
    "event":"Position"
  },
  {
    "user_id":"7778267b-cdff-45c5-9616-4f3b07af9758",
    "match_id":"711c9a67-dd8c-4070-90e4-c606b89c007d.nakama-0",
    "map_id":"GrandRift",
    "x":-25.9025325775,
    "y":29.3601417542,
    "z":47.4134407043,
    "ts":1770716375,
    "event":"Position"
  },
  {
    "user_id":"7778267b-cdff-45c5-9616-4f3b07af9758",
    "match_id":"711c9a67-dd8c-4070-90e4-c606b89c007d.nakama-0",
    "map_id":"GrandRift",
    "x":-26.0999774933,
    "y":27.2525520325,
    "z":66.0204238892,
    "ts":1770716380,
    "event":"Position"
  },
  {
    "user_id":"7778267b-cdff-45c5-9616-4f3b07af9758",
    "match_id":"711c9a67-dd8c-4070-90e4-c606b89c007d.nakama-0",
    "map_id":"GrandRift",
    "x":-24.4218883514,
    "y":27.2455310822,
    "z":64.3561248779,
    "ts":1770716385,
    "event":"Position"
  },
  {
    "user_id":"7778267b-cdff-45c5-9616-4f3b07af9758",
    "match_id":"711c9a67-dd8c-4070-90e4-c606b89c007d.nakama-0",
    "map_id":"GrandRift",
    "x":-34.4393005371,
    "y":27.8751373291,
    "z":69.5988693237,
    "ts":1770716390,
    "event":"Position"
  },
  {
    "user_id":"7778267b-cdff-45c5-9616-4f3b07af9758",
    "match_id":"711c9a67-dd8c-4070-90e4-c606b89c007d.nakama-0",
    "map_id":"GrandRift",
    "x":-52.4402313232,
    "y":33.0960617065,
    "z":87.3955383301,
    "ts":1770716395,
    "event":"Position"
  },
  {
    "user_id":"7778267b-cdff-45c5-9616-4f3b07af9758",
    "match_id":"711c9a67-dd8c-4070-90e4-c606b89c007d.nakama-0",
    "map_id":"GrandRift",
    "x":-43.8691062927,
    "y":33.609664917,
    "z":98.4189605713,
    "ts":1770716400,
    "event":"Position"
  },
  {
    "user_id":"7778267b-cdff-45c5-9616-4f3b07af9758",
    "match_id":"711c9a67-dd8c-4070-90e4-c606b89c007d.nakama-0",
    "map_id":"GrandRift",
    "x":-53.1989517212,
    "y":33.0669059753,
    "z":86.7573928833,
    "ts":1770716405,
    "event":"Position"
  },
  {
    "user_id":"7778267b-cdff-45c5-9616-4f3b07af9758",
    "match_id":"711c9a67-dd8c-4070-90e4-c606b89c007d.nakama-0",
    "map_id":"GrandRift",
    "x":-47.9789848328,
    "y":33.2112464905,
    "z":89.6753768921,
    "ts":1770716410,
    "event":"Position"
  },
  {
    "user_id":"7778267b-cdff-45c5-9616-4f3b07af9758",
    "match_id":"711c9a67-dd8c-4070-90e4-c606b89c007d.nakama-0",
    "map_id":"GrandRift",
    "x":-50.7502059937,
    "y":32.6399040222,
    "z":83.1324691772,
    "ts":1770716415,
    "event":"Position"
  },
  {
    "user_id":"7778267b-cdff-45c5-9616-4f3b07af9758",
    "match_id":"711c9a67-dd8c-4070-90e4-c606b89c007d.nakama-0",
    "map_id":"GrandRift",
    "x":-51.422958374,
    "y":31.9434757233,
    "z":78.9016418457,
    "ts":1770716419,
    "event":"Kill"
  },
  {
    "user_id":"7778267b-cdff-45c5-9616-4f3b07af9758",
    "match_id":"711c9a67-dd8c-4070-90e4-c606b89c007d.nakama-0",
    "map_id":"GrandRift",
    "x":-51.422958374,
    "y":31.9434757233,
    "z":78.9016418457,
    "ts":1770716419,
    "event":"Killed"
  },
  {
    "user_id":"7778267b-cdff-45c5-9616-4f3b07af9758",
    "match_id":"711c9a67-dd8c-4070-90e4-c606b89c007d.nakama-0",
    "map_id":"GrandRift",
    "x":-51.422958374,
    "y":31.9434757233,
    "z":78.9016418457,
    "ts":1770716420,
    "event":"Position"
  }
]