[
  {
    "user_id":"789f8a0b-7d95-443e-bc6a-97a84582bf38",
    "match_id":"a68cf80a-cb02-4f58-b401-0d6fe34da650.nakama-0",
    "map_id":"AmbroseValley",
    "x":267.0387878418,
    "y":110.4187011719,
    "z":-45.1903686523,
    "ts":1770749318,
    "event":"Position"
  },
  {
    "user_id":"789f8a0b-7d95-443e-bc6a-97a84582bf38",
    "match_id":"a68cf80a-cb02-4f58-b401-0d6fe34da650.nakama-0",
    "map_id":"AmbroseValley",
    "x":262.0437011719,
    "y":110.4162902832,
    "z":-46.3826179504,
    "ts":1770749333,
    "event":"Position"
  },
  {
    "user_id":"789f8a0b-7d95-443e-bc6a-97a84582bf38",
    "match_id":"a68cf80a-cb02-4f58-b401-0d6fe34da650.nakama-0",
    "map_id":"AmbroseValley",
    "x":241.529800415,
    "y":110.4255142212,
    "z":-47.0965232849,
    "ts":1770749338,
    "event":"Position"
  },
  {
    "user_id":"789f8a0b-7d95-443e-bc6a-97a84582bf38",
    "match_id":"a68cf80a-cb02-4f58-b401-0d6fe34da650.nakama-0",
    "map_id":"AmbroseValley",
    "x":240.3819732666,
    "y":109.9806213379,
    "z":-44.43932724,
    "ts":1770749342,
    "event":"Loot"
  },
  {
    "user_id":"789f8a0b-7d95-443e-bc6a-97a84582bf38",
    "match_id":"a68cf80a-cb02-4f58-b401-0d6fe34da650.nakama-0",
    "map_id":"AmbroseValley",
    "x":240.3819732666,
    "y":109.9806213379,
    "z":-44.43932724,
    "ts":1770749343,
    "event":"Position"
  },
  {
    "user_id":"789f8a0b-7d95-443e-bc6a-97a84582bf38",
    "match_id":"a68cf80a-cb02-4f58-b401-0d6fe34da650.nakama-0",
    "map_id":"AmbroseValley",
    "x":240.3819732666,
    "y":109.9806213379,
    "z":-44.43932724,
    "ts":1770749344,
    "event":"Loot"
  },
  {
    "user_id":"789f8a0b-7d95-443e-bc6a-97a84582bf38",
    "match_id":"a68cf80a-cb02-4f58-b401-0d6fe34da650.nakama-0",
    "map_id":"AmbroseValley",
    "x":240.3819732666,
    "y":109.9806213379,
    "z":-44.43932724,
    "ts":1770749345,
    "event":"Loot"
  },
  {
    "user_id":"789f8a0b-7d95-443e-bc6a-97a84582bf38",
    "match_id":"a68cf80a-cb02-4f58-b401-0d6fe34da650.nakama-0",
    "map_id":"AmbroseValley",
    "x":237.6867828369,
    "y":110.4000167847,
    "z":-54.7855110168,
    "ts":1770749348,
    "event":"Position"
  },
  {
    "user_id":"789f8a0b-7d95-443e-bc6a-97a84582bf38",
    "match_id":"a68cf80a-cb02-4f58-b401-0d6fe34da650.nakama-0",
    "map_id":"AmbroseValley",
    "x":231.7831573486,
    "y":110.3123397827,
    "z":-77.5133972168,
    "ts":1770749353,
    "event":"Position"
  },
  {
    "user_id":"789f8a0b-7d95-443e-bc6a-97a84582bf38",
    "match_id":"a68cf80a-cb02-4f58-b401-0d6fe34da650.nakama-0",
    "map_id":"AmbroseValley",
    "x":228.0513916016,
    "y":110.9735946655,
    "z":-92.8036727905,
    "ts":1770749359,
    "event":"Position"
  },
  {
    "user_id":"789f8a0b-7d95-443e-bc6a-97a84582bf38",
    "match_id":"a68cf80a-cb02-4f58-b401-0d6fe34da650.nakama-0",
    "map_id":"AmbroseValley",
    "x":216.4999694824,
    "y":111.5729751587,
    "z":-104.2782287598,
    "ts":1770749364,
    "event":"Position"
  },
  {
    "user_id":"789f8a0b-7d95-443e-bc6a-97a84582bf38",
    "match_id":"a68cf80a-cb02-4f58-b401-0d6fe34da650.nakama-0",
    "map_id":"AmbroseValley",
    "x":216.4999694824,
    "y":111.5729751587,
    "z":-104.2782287598,
    "ts":1770749366,
    "event":"Loot"
  },
  {
    "user_id":"789f8a0b-7d95-443e-bc6a-97a84582bf38",
    "match_id":"a68cf80a-cb02-4f58-b401-0d6fe34da650.nakama-0",
    "map_id":"AmbroseValley",
    "x":216.4999694824,
    "y":111.5729751587,
    "z":-104.2782287598,
    "ts":1770749366,
    "event":"Loot"
  },
  {
    "user_id":"789f8a0b-7d95-443e-bc6a-97a84582bf38",
    "match_id":"a68cf80a-cb02-4f58-b401-0d6fe34da650.nakama-0",
    "map_id":"AmbroseValley",
    "x":220.2235412598,
    "y":111.5878143311,
    "z":-108.585105896,
    "ts":1770749369,
    "event":"Position"
  },
  {
    "user_id":"789f8a0b-7d95-443e-bc6a-97a84582bf38",
    "match_id":"a68cf80a-cb02-4f58-b401-0d6fe34da650.nakama-0",
    "map_id":"AmbroseValley",
    "x":216.9993591309,
    "y":111.5878143311,
    "z":-94.7787399292,
    "ts":1770749374,
    "event":"Position"
  },
  {
    "user_id":"789f8a0b-7d95-443e-bc6a-97a84582bf38",
    "match_id":"a68cf80a-cb02-4f58-b401-0d6fe34da650.nakama-0",
    "map_id":"AmbroseValley",
    "x":194.3444824219,
    "y":114.5779800415,
    "z":-83.3524093628,
    "ts":1770749379,
    "event":"Position"
  },
  {
    "user_id":"789f8a0b-7d95-443e-bc6a-97a84582bf38",
    "match_id":"a68cf80a-cb02-4f58-b401-0d6fe34da650.nakama-0",
    "map_id":"AmbroseValley",
    "x":191.2269744873,
    "y":114.3363647461,
    "z":-85.4996337891,
    "ts":1770749383,
    "event":"Loot"
  },
  {
    "user_id":"789f8a0b-7d95-443e-bc6a-97a84582bf38",
    "match_id":"a68cf80a-cb02-4f58-b401-0d6fe34da650.nakama-0",
    "map_id":"AmbroseValley",
    "x":191.2269744873,
    "y":114.3363647461,
    "z":-85.4996337891,
    "ts":1770749384,
    "event":"Position"
  },
  {
    "user_id":"789f8a0b-7d95-443e-bc6a-97a84582bf38",
    "match_id":"a68cf80a-cb02-4f58-b401-0d6fe34da650.nakama-0",
    "map_id":"AmbroseValley",
    "x":194.3191070557,
    "y":114.5829086304,
    "z":-83.4075698853,
    "ts":1770749389,
    "event":"Position"
  },
  {
    "user_id":"789f8a0b-7d95-443e-bc6a-97a84582bf38",
    "match_id":"a68cf80a-cb02-4f58-b401-0d6fe34da650.nakama-0",
    "map_id":"AmbroseValley",
    "x":190.59715271,
    "y":114.8413619995,
    "z":-72.2105178833,
    "ts":1770749394,
    "event":"Position"
  },
  {
    "user_id":"789f8a0b-7d95-443e-bc6a-97a84582bf38",
    "match_id":"a68cf80a-cb02-4f58-b401-0d6fe34da650.nakama-0",
    "map_id":"AmbroseValley",
    "x":174.5293426514,
    "y":110.4011001587,
    "z":-79.1563873291,
    "ts":1770749399,
    "event":"Position"
  },
  {
    "user_id":"789f8a0b-7d95-443e-bc6a-97a84582bf38",
    "match_id":"a68cf80a-cb02-4f58-b401-0d6fe34da650.nakama-0",
    "map_id":"AmbroseValley",
    "x":160.8001251221,
    "y":106.819984436,
    "z":-79.7328643799,
    "ts":1770749404,
    "event":"Position"
  },
  {
    "user_id":"789f8a0b-7d95-443e-bc6a-97a84582bf38",
    "match_id":"a68cf80a-cb02-4f58-b401-0d6fe34da650.nakama-0",
    "map_id":"AmbroseValley",
    "x":158.5330505371,
    "y":106.819984436,
    "z":-80.976524353,
    "ts":1770749409,
    "event":"Position"
  },
  {
    "user_id":"789f8a0b-7d95-443e-bc6a-97a84582bf38",
    "match_id":"a68cf80a-cb02-4f58-b401-0d6fe34da650.nakama-0",
    "map_id":"AmbroseValley",
    "x":158.9729919434,
    "y":106.819984436,
    "z":-78.3179855347,
    "ts":1770749414,
    "event":"Position"
  },
  {
    "user_id":"789f8a0b-7d95-443e-bc6a-97a84582bf38",
    "match_id":"a68cf80a-cb02-4f58-b401-0d6fe34da650.nakama-0",
    "map_id":"AmbroseValley",
    "x":157.5315246582,
    "y":106.819984436,
    "z":-77.5676345825,
    "ts":1770749416,
    "event":"Loot"
  },
  {
    "user_id":"789f8a0b-7d95-443e-bc6a-97a84582bf38",
    "match_id":"a68cf80a-cb02-4f58-b401-0d6fe34da650.nakama-0",
    "map_id":"AmbroseValley",
    "x":158.8354949951,
    "y":106.819984436,
    "z":-72.2834701538,
    "ts":1770749424,
    "event":"Position"
  },
  {
    "user_id":"789f8a0b-7d95-443e-bc6a-97a84582bf38",
    "match_id":"a68cf80a-cb02-4f58-b401-0d6fe34da650.nakama-0",
    "map_id":"AmbroseValley",
    "x":154.7941741943,
    "y":106.819984436,
    "z":-74.1561203003,
    "ts":1770749429,
    "event":"Position"
  },
  {
    "user_id":"789f8a0b-7d95-443e-bc6a-97a84582bf38",
    "match_id":"a68cf80a-cb02-4f58-b401-0d6fe34da650.nakama-0",
    "map_id":"AmbroseValley",
    "x":151.6765441895,
    "y":106.8767242432,
    "z":-77.7042160034,
    "ts":1770749434,
    "event":"Position"
  },
  {
    "user_id":"789f8a0b-7d95-443e-bc6a-97a84582bf38",
    "match_id":"a68cf80a-cb02-4f58-b401-0d6fe34da650.nakama-0",
    "map_id":"AmbroseValley",
    "x":153.6096801758,
    "y":106.8200531006,
    "z":-74.4615097046,
    "ts":1770749444,
    "event":"Position"
  },
  {
    "user_id":"789f8a0b-7d95-443e-bc6a-97a84582bf38",
    "match_id":"a68cf80a-cb02-4f58-b401-0d6fe34da650.nakama-0",
    "map_id":"AmbroseValley",
    "x":161.5283355713,
    "y":106.8200531006,
    "z":-79.9571380615,
    "ts":1770749449,
    "event":"Position"
  },
  {
    "user_id":"789f8a0b-7d95-443e-bc6a-97a84582bf38",
    "match_id":"a68cf80a-cb02-4f58-b401-0d6fe34da650.nakama-0",
    "map_id":"AmbroseValley",
    "x":159.2226409912,
    "y":106.819984436,
    "z":-76.3289031982,
    "ts":1770749454,
    "event":"Position"
  },
  {
    "user_id":"789f8a0b-7d95-443e-bc6a-97a84582bf38",
    "match_id":"a68cf80a-cb02-4f58-b401-0d6fe34da650.nakama-0",
    "map_id":"AmbroseValley",
    "x":150.2948760986,
    "y":106.819984436,
    "z":-78.6634140015,
    "ts":1770749459,
    "event":"Position"
  },
  {
    "user_id":"789f8a0b-7d95-443e-bc6a-97a84582bf38",
    "match_id":"a68cf80a-cb02-4f58-b401-0d6fe34da650.nakama-0",
    "map_id":"AmbroseValley",
    "x":149.8898620605,
    "y":106.819984436,
    "z":-78.5548934937,
    "ts":1770749460,
    "event":"Loot"
  },
  {
    "user_id":"789f8a0b-7d95-443e-bc6a-97a84582bf38",
    "match_id":"a68cf80a-cb02-4f58-b401-0d6fe34da650.nakama-0",
    "map_id":"AmbroseValley",
    "x":140.3798828125,
    "y":106.7020721436,
    "z":-78.2413024902,
    "ts":1770749464,
    "event":"Position"
  },
  {
    "user_id":"789f8a0b-7d95-443e-bc6a-97a84582bf38",
    "match_id":"a68cf80a-cb02-4f58-b401-0d6fe34da650.nakama-0",
    "map_id":"AmbroseValley",
    "x":148.5070953369,
    "y":106.819984436,
    "z":-89.3896331787,
    "ts":1770749468,
    "event":"Loot"
  },
  {
    "user_id":"789f8a0b-7d95-443e-bc6a-97a84582bf38",
    "match_id":"a68cf80a-cb02-4f58-b401-0d6fe34da650.nakama-0",
    "map_id":"AmbroseValley",
    "x":148.5070953369,
    "y":106.819984436,
    "z":-89.3896331787,
    "ts":1770749469,
    "event":"Position"
  },
  {
    "user_id":"789f8a0b-7d95-443e-bc6a-97a84582bf38",
    "match_id":"a68cf80a-cb02-4f58-b401-0d6fe34da650.nakama-0",
    "map_id":"AmbroseValley",
    "x":148.8291015625,
    "y":106.819984436,
    "z":-94.7396850586,
    "ts":1770749473,
    "event":"Loot"
  },
  {
    "user_id":"789f8a0b-7d95-443e-bc6a-97a84582bf38",
    "match_id":"a68cf80a-cb02-4f58-b401-0d6fe34da650.nakama-0",
    "map_id":"AmbroseValley",
    "x":149.6361236572,
    "y":106.819984436,
    "z":-93.7399978638,
    "ts":1770749474,
    "event":"Position"
  },
  {
    "user_id":"789f8a0b-7d95-443e-bc6a-97a84582bf38",
    "match_id":"a68cf80a-cb02-4f58-b401-0d6fe34da650.nakama-0",
    "map_id":"AmbroseValley",
    "x":136.326461792,
    "y":106.7020721436,
    "z":-91.748664856,
    "ts":1770749479,
    "event":"Position"
  },
  {
    "user_id":"789f8a0b-7d95-443e-bc6a-97a84582bf38",
    "match_id":"a68cf80a-cb02-4f58-b401-0d6fe34da650.nakama-0",
    "map_id":"AmbroseValley",
    "x":129.1710662842,
    "y":107.2134780884,
    "z":-119.8386459351,
    "ts":1770749484,
    "event":"Position"
  },
  {
    "user_id":"789f8a0b-7d95-443e-bc6a-97a84582bf38",
    "match_id":"a68cf80a-cb02-4f58-b401-0d6fe34da650.nakama-0",
    "map_id":"AmbroseValley",
    "x":121.0724334717,
    "y":109.0265045166,
    "z":-144.1090087891,
    "ts":1770749489,
    "event":"Position"
  },
  {
    "user_id":"789f8a0b-7d95-443e-bc6a-97a84582bf38",
    "match_id":"a68cf80a-cb02-4f58-b401-0d6fe34da650.nakama-0",
    "map_id":"AmbroseValley",
    "x":109.7688903809,
    "y":112.3748016357,
    "z":-163.0664367676,
    "ts":1770749494,
    "event":"Position"
  },
  {
    "user_id":"789f8a0b-7d95-443e-bc6a-97a84582bf38",
    "match_id":"a68cf80a-cb02-4f58-b401-0d6fe34da650.nakama-0",
    "map_id":"AmbroseValley",
    "x":101.4917373657,
    "y":119.4864807129,
    "z":-193.3036346436,
    "ts":1770749499,
    "event":"Position"
  },
  {
    "user_id":"789f8a0b-7d95-443e-bc6a-97a84582bf38",
    "match_id":"a68cf80a-cb02-4f58-b401-0d6fe34da650.nakama-0",
    "map_id":"AmbroseValley",
    "x":112.8829803467,
    "y":118.9496002197,
    "z":-207.78175354,
    "ts":1770749504,
    "event":"Position"
  },
  {
    "user_id":"789f8a0b-7d95-443e-bc6a-97a84582bf38",
    "match_id":"a68cf80a-cb02-4f58-b401-0d6fe34da650.nakama-0",
    "map_id":"AmbroseValley",
    "x":132.5856323242,
    "y":122.963508606,
    "z":-229.1933441162,
    "ts":1770749509,
    "event":"Position"
  },
  {
    "user_id":"789f8a0b-7d95-443e-bc6a-97a84582bf38",
    "match_id":"a68cf80a-cb02-4f58-b401-0d6fe34da650.nakama-0",
    "map_id":"AmbroseValley",
    "x":130.6483306885,
    "y":123.788444519,
    "z":-233.9226989746,
    "ts":1770749513,
    "event":"Loot"
  },
  {
    "user_id":"789f8a0b-7d95-443e-bc6a-97a84582bf38",
    "match_id":"a68cf80a-cb02-4f58-b401-0d6fe34da650.nakama-0",
    "map_id":"AmbroseValley",
    "x":130.9186401367,
    "y":123.7925796509,
    "z":-233.6908111572,
    "ts":1770749514,
    "event":"Position"
  },
  {
    "user_id":"789f8a0b-7d95-443e-bc6a-97a84582bf38",
    "match_id":"a68cf80a-cb02-4f58-b401-0d6fe34da650.nakama-0",
    "map_id":"AmbroseValley",
    "x":154.5599212646,
    "y":126.4471130371,
    "z":-248.0458831787,
    "ts":1770749519,
    "event":"Position"
  },
  {
    "user_id":"789f8a0b-7d95-443e-bc6a-97a84582bf38",
    "match_id":"a68cf80a-cb02-4f58-b401-0d6fe34da650.nakama-0",
    "map_id":"AmbroseValley",
    "x":167.0091247559,
    "y":127.0188522339,
    "z":-256.2879638672,
    "ts":1770749524,
    "event":"Loot"
  },
  {
    "user_id":"789f8a0b-7d95-443e-bc6a-97a84582bf38",
    "match_id":"a68cf80a-cb02-4f58-b401-0d6fe34da650.nakama-0",
    "map_id":"AmbroseValley",
    "x":167.0091247559,
    "y":127.0188522339,
    "z":-256.2879638672,
    "ts":1770749524,
    "event":"Position"
  },
  {
    "user_id":"789f8a0b-7d95-443e-bc6a-97a84582bf38",
    "match_id":"a68cf80a-cb02-4f58-b401-0d6fe34da650.nakama-0",
    "map_id":"AmbroseValley",
    "x":191.9284362793,
    "y":128.8324737549,
    "z":-260.4522094727,
    "ts":1770749529,
    "event":"Position"
  },
  {
    "user_id":"789f8a0b-7d95-443e-bc6a-97a84582bf38",
    "match_id":"a68cf80a-cb02-4f58-b401-0d6fe34da650.nakama-0",
    "map_id":"AmbroseValley",
    "x":197.9957122803,
    "y":128.9798431396,
    "z":-258.436706543,
    "ts":1770749534,
    "event":"Position"
  },
  {
    "user_id":"789f8a0b-7d95-443e-bc6a-97a84582bf38",
    "match_id":"a68cf80a-cb02-4f58-b401-0d6fe34da650.nakama-0",
    "map_id":"AmbroseValley",
    "x":197.9957122803,
    "y":128.9798431396,
    "z":-258.436706543,
    "ts":1770749536,
    "event":"Loot"
  },
  {
    "user_id":"789f8a0b-7d95-443e-bc6a-97a84582bf38",
    "match_id":"a68cf80a-cb02-4f58-b401-0d6fe34da650.nakama-0",
    "map_id":"AmbroseValley",
    "x":197.5138092041,
    "y":128.9798431396,
    "z":-253.1009979248,
    "ts":1770749540,
    "event":"Position"
  },
  {
    "user_id":"789f8a0b-7d95-443e-bc6a-97a84582bf38",
    "match_id":"a68cf80a-cb02-4f58-b401-0d6fe34da650.nakama-0",
    "map_id":"AmbroseValley",
    "x":199.3171386719,
    "y":128.9798431396,
    "z":-249.996887207,
    "ts":1770749545,
    "event":"Position"
  },
  {
    "user_id":"789f8a0b-7d95-443e-bc6a-97a84582bf38",
    "match_id":"a68cf80a-cb02-4f58-b401-0d6fe34da650.nakama-0",
    "map_id":"AmbroseValley",
    "x":200.2853546143,
    "y":128.9798431396,
    "z":-254.3125915527,
    "ts":1770749550,
    "event":"Loot"
  },
  {
    "user_id":"789f8a0b-7d95-443e-bc6a-97a84582bf38",
    "match_id":"a68cf80a-cb02-4f58-b401-0d6fe34da650.nakama-0",
    "map_id":"AmbroseValley",
    "x":200.2853546143,
    "y":128.9798431396,
    "z":-254.3125915527,
    "ts":1770749550,
    "event":"Position"
  },
  {
    "user_id":"789f8a0b-7d95-443e-bc6a-97a84582bf38",
    "match_id":"a68cf80a-cb02-4f58-b401-0d6fe34da650.nakama-0",
    "map_id":"AmbroseValley",
    "x":196.9731445312,
    "y":128.9798431396,
    "z":-252.9112701416,
    "ts":1770749555,
    "event":"Position"
  },
  {
    "user_id":"789f8a0b-7d95-443e-bc6a-97a84582bf38",
    "match_id":"a68cf80a-cb02-4f58-b401-0d6fe34da650.nakama-0",
    "map_id":"AmbroseValley",
    "x":201.1304779053,
    "y":128.8324737549,
    "z":-258.6504211426,
    "ts":1770749560,
    "event":"Position"
  },
  {
    "user_id":"789f8a0b-7d95-443e-bc6a-97a84582bf38",
    "match_id":"a68cf80a-cb02-4f58-b401-0d6fe34da650.nakama-0",
    "map_id":"AmbroseValley",
    "x":211.7751922607,
    "y":134.4592285156,
    "z":-263.9010314941,
    "ts":1770749565,
    "event":"Position"
  },
  {
    "user_id":"789f8a0b-7d95-443e-bc6a-97a84582bf38",
    "match_id":"a68cf80a-cb02-4f58-b401-0d6fe34da650.nakama-0",
    "map_id":"AmbroseValley",
    "x":207.6663513184,
    "y":128.6231231689,
    "z":-259.7366638184,
    "ts":1770749570,
    "event":"Position"
  },
  {
    "user_id":"789f8a0b-7d95-443e-bc6a-97a84582bf38",
    "match_id":"a68cf80a-cb02-4f58-b401-0d6fe34da650.nakama-0",
    "map_id":"AmbroseValley",
    "x":201.2346191406,
    "y":128.7158660889,
    "z":-272.1855163574,
    "ts":1770749573,
    "event":"Loot"
  },
  {
    "user_id":"789f8a0b-7d95-443e-bc6a-97a84582bf38",
    "match_id":"a68cf80a-cb02-4f58-b401-0d6fe34da650.nakama-0",
    "map_id":"AmbroseValley",
    "x":199.8222808838,
    "y":128.7158660889,
    "z":-274.6157226562,
    "ts":1770749575,
    "event":"Position"
  },
  {
    "user_id":"789f8a0b-7d95-443e-bc6a-97a84582bf38",
    "match_id":"a68cf80a-cb02-4f58-b401-0d6fe34da650.nakama-0",
    "map_id":"AmbroseValley",
    "x":185.3475036621,
    "y":128.7158660889,
    "z":-292.3414611816,
    "ts":1770749580,
    "event":"Position"
  },
  {
    "user_id":"789f8a0b-7d95-443e-bc6a-97a84582bf38",
    "match_id":"a68cf80a-cb02-4f58-b401-0d6fe34da650.nakama-0",
    "map_id":"AmbroseValley",
    "x":176.7660064697,
    "y":128.7909698486,
    "z":-299.7405090332,
    "ts":1770749584,
    "event":"Loot"
  },
  {
    "user_id":"789f8a0b-7d95-443e-bc6a-97a84582bf38",
    "match_id":"a68cf80a-cb02-4f58-b401-0d6fe34da650.nakama-0",
    "map_id":"AmbroseValley",
    "x":176.7660064697,
    "y":128.7909698486,
    "z":-299.7405090332,
    "ts":1770749585,
    "event":"Position"
  },
  {
    "user_id":"789f8a0b-7d95-443e-bc6a-97a84582bf38",
    "match_id":"a68cf80a-cb02-4f58-b401-0d6fe34da650.nakama-0",
    "map_id":"AmbroseValley",
    "x":168.3803863525,
    "y":128.7909698486,
    "z":-296.525177002,
    "ts":1770749589,
    "event":"Loot"
  },
  {
    "user_id":"789f8a0b-7d95-443e-bc6a-97a84582bf38",
    "match_id":"a68cf80a-cb02-4f58-b401-0d6fe34da650.nakama-0",
    "map_id":"AmbroseValley",
    "x":168.3803863525,
    "y":128.7909698486,
    "z":-296.525177002,
    "ts":1770749590,
    "event":"Position"
  },
  {
    "user_id":"789f8a0b-7d95-443e-bc6a-97a84582bf38",
    "match_id":"a68cf80a-cb02-4f58-b401-0d6fe34da650.nakama-0",
    "map_id":"AmbroseValley",
    "x":166.572845459,
    "y":128.7909698486,
    "z":-292.335723877,
    "ts":1770749592,
    "event":"Loot"
  },
  {
    "user_id":"789f8a0b-7d95-443e-bc6a-97a84582bf38",
    "match_id":"a68cf80a-cb02-4f58-b401-0d6fe34da650.nakama-0",
    "map_id":"AmbroseValley",
    "x":164.892074585,
    "y":128.7909698486,
    "z":-294.6765136719,
    "ts":1770749595,
    "event":"Position"
  },
  {
    "user_id":"789f8a0b-7d95-443e-bc6a-97a84582bf38",
    "match_id":"a68cf80a-cb02-4f58-b401-0d6fe34da650.nakama-0",
    "map_id":"AmbroseValley",
    "x":167.7261657715,
    "y":128.7909698486,
    "z":-292.8706054688,
    "ts":1770749600,
    "event":"Position"
  },
  {
    "user_id":"789f8a0b-7d95-443e-bc6a-97a84582bf38",
    "match_id":"a68cf80a-cb02-4f58-b401-0d6fe34da650.nakama-0",
    "map_id":"AmbroseValley",
    "x":171.119644165,
    "y":128.7909698486,
    "z":-290.3013916016,
    "ts":1770749605,
    "event":"Position"
  },
  {
    "user_id":"789f8a0b-7d95-443e-bc6a-97a84582bf38",
    "match_id":"a68cf80a-cb02-4f58-b401-0d6fe34da650.nakama-0",
    "map_id":"AmbroseValley",
    "x":174.3156280518,
    "y":128.7909698486,
    "z":-294.6054382324,
    "ts":1770749610,
    "event":"Loot"
  },
  {
    "user_id":"789f8a0b-7d95-443e-bc6a-97a84582bf38",
    "match_id":"a68cf80a-cb02-4f58-b401-0d6fe34da650.nakama-0",
    "map_id":"AmbroseValley",
    "x":174.3237304688,
    "y":128.7909698486,
    "z":-288.6054382324,
    "ts":1770749615,
    "event":"Position"
  },
  {
    "user_id":"789f8a0b-7d95-443e-bc6a-97a84582bf38",
    "match_id":"a68cf80a-cb02-4f58-b401-0d6fe34da650.nakama-0",
    "map_id":"AmbroseValley",
    "x":177.3688812256,
    "y":128.7909698486,
    "z":-287.6563415527,
    "ts":1770749625,
    "event":"Position"
  },
  {
    "user_id":"789f8a0b-7d95-443e-bc6a-97a84582bf38",
    "match_id":"a68cf80a-cb02-4f58-b401-0d6fe34da650.nakama-0",
    "map_id":"AmbroseValley",
    "x":168.6898498535,
    "y":128.7909698486,
    "z":-298.0191040039,
    "ts":1770749630,
    "event":"Position"
  },
  {
    "user_id":"789f8a0b-7d95-443e-bc6a-97a84582bf38",
    "match_id":"a68cf80a-cb02-4f58-b401-0d6fe34da650.nakama-0",
    "map_id":"AmbroseValley",
    "x":169.5659484863,
    "y":128.9326629639,
    "z":-311.0516662598,
    "ts":1770749635,
    "event":"Position"
  },
  {
    "user_id":"789f8a0b-7d95-443e-bc6a-97a84582bf38",
    "match_id":"a68cf80a-cb02-4f58-b401-0d6fe34da650.nakama-0",
    "map_id":"AmbroseValley",
    "x":153.5780029297,
    "y":128.3830718994,
    "z":-333.8827514648,
    "ts":1770749640,
    "event":"Position"
  },
  {
    "user_id":"789f8a0b-7d95-443e-bc6a-97a84582bf38",
    "match_id":"a68cf80a-cb02-4f58-b401-0d6fe34da650.nakama-0",
    "map_id":"AmbroseValley",
    "x":146.6139831543,
    "y":128.6696472168,
    "z":-345.6508178711,
    "ts":1770749645,
    "event":"Loot"
  },
  {
    "user_id":"789f8a0b-7d95-443e-bc6a-97a84582bf38",
    "match_id":"a68cf80a-cb02-4f58-b401-0d6fe34da650.nakama-0",
    "map_id":"AmbroseValley",
    "x":146.6139831543,
    "y":128.6696472168,
    "z":-345.6508178711,
    "ts":1770749645,
    "event":"Position"
  },
  {
    "user_id":"789f8a0b-7d95-443e-bc6a-97a84582bf38",
    "match_id":"a68cf80a-cb02-4f58-b401-0d6fe34da650.nakama-0",
    "map_id":"AmbroseValley",
    "x":147.8201446533,
    "y":128.6696472168,
    "z":-351.1624450684,
    "ts":1770749648,
    "event":"Loot"
  },
  {
    "user_id":"789f8a0b-7d95-443e-bc6a-97a84582bf38",
    "match_id":"a68cf80a-cb02-4f58-b401-0d6fe34da650.nakama-0",
    "map_id":"AmbroseValley",
    "x":147.8201446533,
    "y":128.6696472168,
    "z":-351.1624450684,
    "ts":1770749648,
    "event":"Loot"
  },
  {
    "user_id":"789f8a0b-7d95-443e-bc6a-97a84582bf38",
    "match_id":"a68cf80a-cb02-4f58-b401-0d6fe34da650.nakama-0",
    "map_id":"AmbroseValley",
    "x":147.8201446533,
    "y":128.6696472168,
    "z":-351.1624450684,
    "ts":1770749648,
    "event":"Loot"
  },
  {
    "user_id":"789f8a0b-7d95-443e-bc6a-97a84582bf38",
    "match_id":"a68cf80a-cb02-4f58-b401-0d6fe34da650.nakama-0",
    "map_id":"AmbroseValley",
    "x":147.8201446533,
    "y":128.6696472168,
    "z":-351.1624450684,
    "ts":1770749648,
    "event":"Loot"
  },
  {
    "user_id":"789f8a0b-7d95-443e-bc6a-97a84582bf38",
    "match_id":"a68cf80a-cb02-4f58-b401-0d6fe34da650.nakama-0",
    "map_id":"AmbroseValley",
    "x":142.4403839111,
    "y":128.6696472168,
    "z":-352.5057983398,
    "ts":1770749655,
    "event":"Position"
  },
  {
    "user_id":"789f8a0b-7d95-443e-bc6a-97a84582bf38",
    "match_id":"a68cf80a-cb02-4f58-b401-0d6fe34da650.nakama-0",
    "map_id":"AmbroseValley",
    "x":138.5515289307,
    "y":128.6696472168,
    "z":-356.9167480469,
    "ts":1770749660,
    "event":"Position"
  },
  {
    "user_id":"789f8a0b-7d95-443e-bc6a-97a84582bf38",
    "match_id":"a68cf80a-cb02-4f58-b401-0d6fe34da650.nakama-0",
    "map_id":"AmbroseValley",
    "x":142.812210083,
    "y":128.6696472168,
    "z":-352.6938171387,
    "ts":1770749680,
    "event":"Position"
  },
  {
    "user_id":"789f8a0b-7d95-443e-bc6a-97a84582bf38",
    "match_id":"a68cf80a-cb02-4f58-b401-0d6fe34da650.nakama-0",
    "map_id":"AmbroseValley",
    "x":136.5854034424,
    "y":128.6696472168,
    "z":-351.8499145508,
    "ts":1770749685,
    "event":"Position"
  },
  {
    "user_id":"789f8a0b-7d95-443e-bc6a-97a84582bf38",
    "match_id":"a68cf80a-cb02-4f58-b401-0d6fe34da650.nakama-0",
    "map_id":"AmbroseValley",
    "x":141.3335571289,
    "y":128.6696472168,
    "z":-340.8258972168,
    "ts":1770749690,
    "event":"Position"
  },
  {
    "user_id":"789f8a0b-7d95-443e-bc6a-97a84582bf38",
    "match_id":"a68cf80a-cb02-4f58-b401-0d6fe34da650.nakama-0",
    "map_id":"AmbroseValley",
    "x":143.4488220215,
    "y":128.6696472168,
    "z":-338.4925537109,
    "ts":1770749692,
    "event":"Loot"
  },
  {
    "user_id":"789f8a0b-7d95-443e-bc6a-97a84582bf38",
    "match_id":"a68cf80a-cb02-4f58-b401-0d6fe34da650.nakama-0",
    "map_id":"AmbroseValley",
    "x":142.8520050049,
    "y":128.6696472168,
    "z":-337.2749023438,
    "ts":1770749694,
    "event":"Loot"
  },
  {
    "user_id":"789f8a0b-7d95-443e-bc6a-97a84582bf38",
    "match_id":"a68cf80a-cb02-4f58-b401-0d6fe34da650.nakama-0",
    "map_id":"AmbroseValley",
    "x":141.1634063721,
    "y":128.6696472168,
    "z":-336.6098327637,
    "ts":1770749695,
    "event":"Position"
  },
  {
    "user_id":"789f8a0b-7d95-443e-bc6a-97a84582bf38",
    "match_id":"a68cf80a-cb02-4f58-b401-0d6fe34da650.nakama-0",
    "map_id":"AmbroseValley",
    "x":138.9059753418,
    "y":128.6696472168,
    "z":-332.8498535156,
    "ts":1770749700,
    "event":"Position"
  },
  {
    "user_id":"789f8a0b-7d95-443e-bc6a-97a84582bf38",
    "match_id":"a68cf80a-cb02-4f58-b401-0d6fe34da650.nakama-0",
    "map_id":"AmbroseValley",
    "x":129.1902618408,
    "y":128.4054870605,
    "z":-338.2485351562,
    "ts":1770749705,
    "event":"Position"
  },
  {
    "user_id":"789f8a0b-7d95-443e-bc6a-97a84582bf38",
    "match_id":"a68cf80a-cb02-4f58-b401-0d6fe34da650.nakama-0",
    "map_id":"AmbroseValley",
    "x":113.2555465698,
    "y":128.7234039307,
    "z":-338.0110778809,
    "ts":1770749710,
    "event":"Position"
  },
  {
    "user_id":"789f8a0b-7d95-443e-bc6a-97a84582bf38",
    "match_id":"a68cf80a-cb02-4f58-b401-0d6fe34da650.nakama-0",
    "map_id":"AmbroseValley",
    "x":88.8344726562,
    "y":126.8193511963,
    "z":-339.6903076172,
    "ts":1770749716,
    "event":"Position"
  },
  {
    "user_id":"789f8a0b-7d95-443e-bc6a-97a84582bf38",
    "match_id":"a68cf80a-cb02-4f58-b401-0d6fe34da650.nakama-0",
    "map_id":"AmbroseValley",
    "x":73.3531646729,
    "y":126.3202514648,
    "z":-331.3157348633,
    "ts":1770749721,
    "event":"Position"
  },
  {
    "user_id":"789f8a0b-7d95-443e-bc6a-97a84582bf38",
    "match_id":"a68cf80a-cb02-4f58-b401-0d6fe34da650.nakama-0",
    "map_id":"AmbroseValley",
    "x":49.7636413574,
    "y":125.1676559448,
    "z":-333.0089416504,
    "ts":1770749726,
    "event":"Position"
  },
  {
    "user_id":"789f8a0b-7d95-443e-bc6a-97a84582bf38",
    "match_id":"a68cf80a-cb02-4f58-b401-0d6fe34da650.nakama-0",
    "map_id":"AmbroseValley",
    "x":48.6469955444,
    "y":125.1676559448,
    "z":-331.2354736328,
    "ts":1770749727,
    "event":"Loot"
  },
  {
    "user_id":"789f8a0b-7d95-443e-bc6a-97a84582bf38",
    "match_id":"a68cf80a-cb02-4f58-b401-0d6fe34da650.nakama-0",
    "map_id":"AmbroseValley",
    "x":48.3754234314,
    "y":125.1676559448,
    "z":-329.7622680664,
    "ts":1770749731,
    "event":"Position"
  },
  {
    "user_id":"789f8a0b-7d95-443e-bc6a-97a84582bf38",
    "match_id":"a68cf80a-cb02-4f58-b401-0d6fe34da650.nakama-0",
    "map_id":"AmbroseValley",
    "x":48.393371582,
    "y":125.1676559448,
    "z":-329.809753418,
    "ts":1770749732,
    "event":"Loot"
  },
  {
    "user_id":"789f8a0b-7d95-443e-bc6a-97a84582bf38",
    "match_id":"a68cf80a-cb02-4f58-b401-0d6fe34da650.nakama-0",
    "map_id":"AmbroseValley",
    "x":54.6037025452,
    "y":125.1676559448,
    "z":-322.979095459,
    "ts":1770749736,
    "event":"Position"
  },
  {
    "user_id":"789f8a0b-7d95-443e-bc6a-97a84582bf38",
    "match_id":"a68cf80a-cb02-4f58-b401-0d6fe34da650.nakama-0",
    "map_id":"AmbroseValley",
    "x":48.708782196,
    "y":125.1676559448,
    "z":-320.3019714355,
    "ts":1770749741,
    "event":"Position"
  },
  {
    "user_id":"789f8a0b-7d95-443e-bc6a-97a84582bf38",
    "match_id":"a68cf80a-cb02-4f58-b401-0d6fe34da650.nakama-0",
    "map_id":"AmbroseValley",
    "x":43.4199752808,
    "y":125.1676483154,
    "z":-322.1040344238,
    "ts":1770749751,
    "event":"Position"
  },
  {
    "user_id":"789f8a0b-7d95-443e-bc6a-97a84582bf38",
    "match_id":"a68cf80a-cb02-4f58-b401-0d6fe34da650.nakama-0",
    "map_id":"AmbroseValley",
    "x":41.0552368164,
    "y":125.1676483154,
    "z":-320.7628173828,
    "ts":1770749766,
    "event":"Loot"
  },
  {
    "user_id":"789f8a0b-7d95-443e-bc6a-97a84582bf38",
    "match_id":"a68cf80a-cb02-4f58-b401-0d6fe34da650.nakama-0",
    "map_id":"AmbroseValley",
    "x":48.9559211731,
    "y":125.1676559448,
    "z":-321.5794372559,
    "ts":1770749781,
    "event":"Position"
  },
  {
    "user_id":"789f8a0b-7d95-443e-bc6a-97a84582bf38",
    "match_id":"a68cf80a-cb02-4f58-b401-0d6fe34da650.nakama-0",
    "map_id":"AmbroseValley",
    "x":49.0674514771,
    "y":124.9954223633,
    "z":-306.1993713379,
    "ts":1770749786,
    "event":"Position"
  },
  {
    "user_id":"789f8a0b-7d95-443e-bc6a-97a84582bf38",
    "match_id":"a68cf80a-cb02-4f58-b401-0d6fe34da650.nakama-0",
    "map_id":"AmbroseValley",
    "x":51.9757652283,
    "y":125.0201034546,
    "z":-300.404876709,
    "ts":1770749791,
    "event":"Position"
  },
  {
    "user_id":"789f8a0b-7d95-443e-bc6a-97a84582bf38",
    "match_id":"a68cf80a-cb02-4f58-b401-0d6fe34da650.nakama-0",
    "map_id":"AmbroseValley",
    "x":52.8483276367,
    "y":125.0041427612,
    "z":-294.0773925781,
    "ts":1770749796,
    "event":"Position"
  },
  {
    "user_id":"789f8a0b-7d95-443e-bc6a-97a84582bf38",
    "match_id":"a68cf80a-cb02-4f58-b401-0d6fe34da650.nakama-0",
    "map_id":"AmbroseValley",
    "x":43.6717453003,
    "y":125.0213317871,
    "z":-288.9450683594,
    "ts":1770749801,
    "event":"Position"
  },
  {
    "user_id":"789f8a0b-7d95-443e-bc6a-97a84582bf38",
    "match_id":"a68cf80a-cb02-4f58-b401-0d6fe34da650.nakama-0",
    "map_id":"AmbroseValley",
    "x":40.6131439209,
    "y":125.0228042603,
    "z":-287.5030212402,
    "ts":1770749802,
    "event":"BotKill"
  },
  {
    "user_id":"789f8a0b-7d95-443e-bc6a-97a84582bf38",
    "match_id":"a68cf80a-cb02-4f58-b401-0d6fe34da650.nakama-0",
    "map_id":"AmbroseValley",
    "x":35.8358535767,
    "y":125.0228042603,
    "z":-286.332611084,
    "ts":1770749806,
    "event":"Position"
  },
  {
    "user_id":"789f8a0b-7d95-443e-bc6a-97a84582bf38",
    "match_id":"a68cf80a-cb02-4f58-b401-0d6fe34da650.nakama-0",
    "map_id":"AmbroseValley",
    "x":35.8358535767,
    "y":125.0228042603,
    "z":-286.332611084,
    "ts":1770749807,
    "event":"Loot"
  },
  {
    "user_id":"789f8a0b-7d95-443e-bc6a-97a84582bf38",
    "match_id":"a68cf80a-cb02-4f58-b401-0d6fe34da650.nakama-0",
    "map_id":"AmbroseValley",
    "x":35.8358535767,
    "y":125.0228042603,
    "z":-286.332611084,
    "ts":1770749809,
    "event":"Loot"
  },
  {
    "user_id":"789f8a0b-7d95-443e-bc6a-97a84582bf38",
    "match_id":"a68cf80a-cb02-4f58-b401-0d6fe34da650.nakama-0",
    "map_id":"AmbroseValley",
    "x":19.7739200592,
    "y":125.1594619751,
    "z":-275.7909851074,
    "ts":1770749821,
    "event":"Position"
  },
  {
    "user_id":"789f8a0b-7d95-443e-bc6a-97a84582bf38",
    "match_id":"a68cf80a-cb02-4f58-b401-0d6fe34da650.nakama-0",
    "map_id":"AmbroseValley",
    "x":14.9649381638,
    "y":125.2344207764,
    "z":-247.9095001221,
    "ts":1770749826,
    "event":"Position"
  },
  {
    "user_id":"789f8a0b-7d95-443e-bc6a-97a84582bf38",
    "match_id":"a68cf80a-cb02-4f58-b401-0d6fe34da650.nakama-0",
    "map_id":"AmbroseValley",
    "x":-4.8898115158,
    "y":125.4358444214,
    "z":-231.8375854492,
    "ts":1770749831,
    "event":"Position"
  },
  {
    "user_id":"789f8a0b-7d95-443e-bc6a-97a84582bf38",
    "match_id":"a68cf80a-cb02-4f58-b401-0d6fe34da650.nakama-0",
    "map_id":"AmbroseValley",
    "x":-21.1242866516,
    "y":122.0366668701,
    "z":-215.4179077148,
    "ts":1770749836,
    "event":"Position"
  },
  {
    "user_id":"789f8a0b-7d95-443e-bc6a-97a84582bf38",
    "match_id":"a68cf80a-cb02-4f58-b401-0d6fe34da650.nakama-0",
    "map_id":"AmbroseValley",
    "x":-6.6583170891,
    "y":119.8226623535,
    "z":-192.1611633301,
    "ts":1770749841,
    "event":"Position"
  },
  {
    "user_id":"789f8a0b-7d95-443e-bc6a-97a84582bf38",
    "match_id":"a68cf80a-cb02-4f58-b401-0d6fe34da650.nakama-0",
    "map_id":"AmbroseValley",
    "x":-4.7473344803,
    "y":115.7113494873,
    "z":-167.2758331299,
    "ts":1770749846,
    "event":"Position"
  },
  {
    "user_id":"789f8a0b-7d95-443e-bc6a-97a84582bf38",
    "match_id":"a68cf80a-cb02-4f58-b401-0d6fe34da650.nakama-0",
    "map_id":"AmbroseValley",
    "x":-2.600477457,
    "y":114.8087463379,
    "z":-160.1342163086,
    "ts":1770749851,
    "event":"Position"
  },
  {
    "user_id":"789f8a0b-7d95-443e-bc6a-97a84582bf38",
    "match_id":"a68cf80a-cb02-4f58-b401-0d6fe34da650.nakama-0",
    "map_id":"AmbroseValley",
    "x":-2.600477457,
    "y":114.8087463379,
    "z":-160.1342163086,
    "ts":1770749851,
    "event":"Loot"
  },
  {
    "user_id":"789f8a0b-7d95-443e-bc6a-97a84582bf38",
    "match_id":"a68cf80a-cb02-4f58-b401-0d6fe34da650.nakama-0",
    "map_id":"AmbroseValley",
    "x":6.5874252319,
    "y":113.7356262207,
    "z":-144.613861084,
    "ts":1770749856,
    "event":"Position"
  },
  {
    "user_id":"789f8a0b-7d95-443e-bc6a-97a84582bf38",
    "match_id":"a68cf80a-cb02-4f58-b401-0d6fe34da650.nakama-0",
    "map_id":"AmbroseValley",
    "x":1.9571275711,
    "y":110.0611419678,
    "z":-119.5216445923,
    "ts":1770749861,
    "event":"Position"
  },
  {
    "user_id":"789f8a0b-7d95-443e-bc6a-97a84582bf38",
    "match_id":"a68cf80a-cb02-4f58-b401-0d6fe34da650.nakama-0",
    "map_id":"AmbroseValley",
    "x":-8.2462911606,
    "y":108.1699523926,
    "z":-100.6871032715,
    "ts":1770749866,
    "event":"Position"
  },
  {
    "user_id":"789f8a0b-7d95-443e-bc6a-97a84582bf38",
    "match_id":"a68cf80a-cb02-4f58-b401-0d6fe34da650.nakama-0",
    "map_id":"AmbroseValley",
    "x":-27.6239948273,
    "y":106.8538284302,
    "z":-83.6008682251,
    "ts":1770749871,
    "event":"Position"
  },
  {
    "user_id":"789f8a0b-7d95-443e-bc6a-97a84582bf38",
    "match_id":"a68cf80a-cb02-4f58-b401-0d6fe34da650.nakama-0",
    "map_id":"AmbroseValley",
    "x":-39.6344718933,
    "y":107.562713623,
    "z":-81.7979812622,
    "ts":1770749875,
    "event":"BotKill"
  },
  {
    "user_id":"789f8a0b-7d95-443e-bc6a-97a84582bf38",
    "match_id":"a68cf80a-cb02-4f58-b401-0d6fe34da650.nakama-0",
    "map_id":"AmbroseValley",
    "x":-45.1966514587,
    "y":107.5825805664,
    "z":-80.5243911743,
    "ts":1770749876,
    "event":"Position"
  },
  {
    "user_id":"789f8a0b-7d95-443e-bc6a-97a84582bf38",
    "match_id":"a68cf80a-cb02-4f58-b401-0d6fe34da650.nakama-0",
    "map_id":"AmbroseValley",
    "x":-52.2036933899,
    "y":107.6176528931,
    "z":-80.3386459351,
    "ts":1770749880,
    "event":"Loot"
  },
  {
    "user_id":"789f8a0b-7d95-443e-bc6a-97a84582bf38",
    "match_id":"a68cf80a-cb02-4f58-b401-0d6fe34da650.nakama-0",
    "map_id":"AmbroseValley",
    "x":-54.6729888916,
    "y":107.6176528931,
    "z":-76.611946106,
    "ts":1770749881,
    "event":"Position"
  },
  {
    "user_id":"789f8a0b-7d95-443e-bc6a-97a84582bf38",
    "match_id":"a68cf80a-cb02-4f58-b401-0d6fe34da650.nakama-0",
    "map_id":"AmbroseValley",
    "x":-66.9186172485,
    "y":107.5845413208,
    "z":-65.6245498657,
    "ts":1770749886,
    "event":"Position"
  },
  {
    "user_id":"789f8a0b-7d95-443e-bc6a-97a84582bf38",
    "match_id":"a68cf80a-cb02-4f58-b401-0d6fe34da650.nakama-0",
    "map_id":"AmbroseValley",
    "x":-59.8917961121,
    "y":107.544128418,
    "z":-71.7195281982,
    "ts":1770749891,
    "event":"Position"
  },
  {
    "user_id":"789f8a0b-7d95-443e-bc6a-97a84582bf38",
    "match_id":"a68cf80a-cb02-4f58-b401-0d6fe34da650.nakama-0",
    "map_id":"AmbroseValley",
    "x":-61.3268051147,
    "y":106.7216567993,
    "z":-85.0347290039,
    "ts":1770749897,
    "event":"Position"
  },
  {
    "user_id":"789f8a0b-7d95-443e-bc6a-97a84582bf38",
    "match_id":"a68cf80a-cb02-4f58-b401-0d6fe34da650.nakama-0",
    "map_id":"AmbroseValley",
    "x":-72.2880020142,
    "y":106.412071228,
    "z":-92.8325805664,
    "ts":1770749902,
    "event":"Position"
  },
  {
    "user_id":"789f8a0b-7d95-443e-bc6a-97a84582bf38",
    "match_id":"a68cf80a-cb02-4f58-b401-0d6fe34da650.nakama-0",
    "map_id":"AmbroseValley",
    "x":-96.6755447388,
    "y":106.1258850098,
    "z":-93.5787734985,
    "ts":1770749907,
    "event":"Position"
  },
  {
    "user_id":"789f8a0b-7d95-443e-bc6a-97a84582bf38",
    "match_id":"a68cf80a-cb02-4f58-b401-0d6fe34da650.nakama-0",
    "map_id":"AmbroseValley",
    "x":-110.2590103149,
    "y":104.9585494995,
    "z":-74.162979126,
    "ts":1770749912,
    "event":"Position"
  },
  {
    "user_id":"789f8a0b-7d95-443e-bc6a-97a84582bf38",
    "match_id":"a68cf80a-cb02-4f58-b401-0d6fe34da650.nakama-0",
    "map_id":"AmbroseValley",
    "x":-120.0592575073,
    "y":104.9441452026,
    "z":-62.4870109558,
    "ts":1770749917,
    "event":"Position"
  },
  {
    "user_id":"789f8a0b-7d95-443e-bc6a-97a84582bf38",
    "match_id":"a68cf80a-cb02-4f58-b401-0d6fe34da650.nakama-0",
    "map_id":"AmbroseValley",
    "x":-103.6295471191,
    "y":104.9990844727,
    "z":-49.54637146,
    "ts":1770749922,
    "event":"Position"
  },
  {
    "user_id":"789f8a0b-7d95-443e-bc6a-97a84582bf38",
    "match_id":"a68cf80a-cb02-4f58-b401-0d6fe34da650.nakama-0",
    "map_id":"AmbroseValley",
    "x":-102.8803939819,
    "y":105.0010528564,
    "z":-48.283164978,
    "ts":1770749923,
    "event":"BotKill"
  },
  {
    "user_id":"789f8a0b-7d95-443e-bc6a-97a84582bf38",
    "match_id":"a68cf80a-cb02-4f58-b401-0d6fe34da650.nakama-0",
    "map_id":"AmbroseValley",
    "x":-102.0525588989,
    "y":105.003074646,
    "z":-50.2948036194,
    "ts":1770749927,
    "event":"Position"
  },
  {
    "user_id":"789f8a0b-7d95-443e-bc6a-97a84582bf38",
    "match_id":"a68cf80a-cb02-4f58-b401-0d6fe34da650.nakama-0",
    "map_id":"AmbroseValley",
    "x":-100.2104263306,
    "y":105.0059738159,
    "z":-44.5132102966,
    "ts":1770749932,
    "event":"Position"
  },
  {
    "user_id":"789f8a0b-7d95-443e-bc6a-97a84582bf38",
    "match_id":"a68cf80a-cb02-4f58-b401-0d6fe34da650.nakama-0",
    "map_id":"AmbroseValley",
    "x":-100.2104263306,
    "y":105.0059738159,
    "z":-44.5132102966,
    "ts":1770749932,
    "event":"Loot"
  },
  {
    "user_id":"789f8a0b-7d95-443e-bc6a-97a84582bf38",
    "match_id":"a68cf80a-cb02-4f58-b401-0d6fe34da650.nakama-0",
    "map_id":"AmbroseValley",
    "x":-100.2104263306,
    "y":105.0059738159,
    "z":-44.5132102966,
    "ts":1770749934,
    "event":"Loot"
  },
  {
    "user_id":"789f8a0b-7d95-443e-bc6a-97a84582bf38",
    "match_id":"a68cf80a-cb02-4f58-b401-0d6fe34da650.nakama-0",
    "map_id":"AmbroseValley",
    "x":-98.9238967896,
    "y":104.9979095459,
    "z":-39.8012619019,
    "ts":1770749937,
    "event":"Loot"
  },
  {
    "user_id":"789f8a0b-7d95-443e-bc6a-97a84582bf38",
    "match_id":"a68cf80a-cb02-4f58-b401-0d6fe34da650.nakama-0",
    "map_id":"AmbroseValley",
    "x":-98.9238967896,
    "y":104.9979095459,
    "z":-39.8012619019,
    "ts":1770749937,
    "event":"Position"
  },
  {
    "user_id":"789f8a0b-7d95-443e-bc6a-97a84582bf38",
    "match_id":"a68cf80a-cb02-4f58-b401-0d6fe34da650.nakama-0",
    "map_id":"AmbroseValley",
    "x":-101.1002960205,
    "y":104.9807739258,
    "z":-36.9062347412,
    "ts":1770749942,
    "event":"Position"
  },
  {
    "user_id":"789f8a0b-7d95-443e-bc6a-97a84582bf38",
    "match_id":"a68cf80a-cb02-4f58-b401-0d6fe34da650.nakama-0",
    "map_id":"AmbroseValley",
    "x":-101.7867584229,
    "y":109.3725357056,
    "z":-42.609249115,
    "ts":1770749947,
    "event":"Position"
  },
  {
    "user_id":"789f8a0b-7d95-443e-bc6a-97a84582bf38",
    "match_id":"a68cf80a-cb02-4f58-b401-0d6fe34da650.nakama-0",
    "map_id":"AmbroseValley",
    "x":-91.6485977173,
    "y":104.555480957,
    "z":-42.3729476929,
    "ts":1770749957,
    "event":"Position"
  },
  {
    "user_id":"789f8a0b-7d95-443e-bc6a-97a84582bf38",
    "match_id":"a68cf80a-cb02-4f58-b401-0d6fe34da650.nakama-0",
    "map_id":"AmbroseValley",
    "x":-90.0854721069,
    "y":104.1240692139,
    "z":-40.0061950684,
    "ts":1770749958,
    "event":"BotKill"
  },
  {
    "user_id":"789f8a0b-7d95-443e-bc6a-97a84582bf38",
    "match_id":"a68cf80a-cb02-4f58-b401-0d6fe34da650.nakama-0",
    "map_id":"AmbroseValley",
    "x":-88.3049316406,
    "y":103.7108078003,
    "z":-38.2505264282,
    "ts":1770749962,
    "event":"Position"
  },
  {
    "user_id":"789f8a0b-7d95-443e-bc6a-97a84582bf38",
    "match_id":"a68cf80a-cb02-4f58-b401-0d6fe34da650.nakama-0",
    "map_id":"AmbroseValley",
    "x":-90.8498153687,
    "y":103.895072937,
    "z":-34.41563797,
    "ts":1770749967,
    "event":"Position"
  },
  {
    "user_id":"789f8a0b-7d95-443e-bc6a-97a84582bf38",
    "match_id":"a68cf80a-cb02-4f58-b401-0d6fe34da650.nakama-0",
    "map_id":"AmbroseValley",
    "x":-98.5744400024,
    "y":104.9779968262,
    "z":-45.3012390137,
    "ts":1770749972,
    "event":"Position"
  },
  {
    "user_id":"789f8a0b-7d95-443e-bc6a-97a84582bf38",
    "match_id":"a68cf80a-cb02-4f58-b401-0d6fe34da650.nakama-0",
    "map_id":"AmbroseValley",
    "x":-99.3470916748,
    "y":105.0099105835,
    "z":-45.7637672424,
    "ts":1770749977,
    "event":"Position"
  },
  {
    "user_id":"789f8a0b-7d95-443e-bc6a-97a84582bf38",
    "match_id":"a68cf80a-cb02-4f58-b401-0d6fe34da650.nakama-0",
    "map_id":"AmbroseValley",
    "x":-100.1165618896,
    "y":105.0116119385,
    "z":-42.4195289612,
    "ts":1770749982,
    "event":"Position"
  },
  {
    "user_id":"789f8a0b-7d95-443e-bc6a-97a84582bf38",
    "match_id":"a68cf80a-cb02-4f58-b401-0d6fe34da650.nakama-0",
    "map_id":"AmbroseValley",
    "x":-100.7099685669,
    "y":105.0043029785,
    "z":-43.0552482605,
    "ts":1770749984,
    "event":"BotKilled"
  }
]